valid_flow_engine/__init__.py
valid_flow_engine/engine/__init__.py
valid_flow_engine/engine/execute.py
valid_flow_engine/engine/invocation.py
valid_flow_engine/engine/node/__init__.py
valid_flow_engine/engine/node/action.py
valid_flow_engine/engine/node/bool.py
valid_flow_engine/engine/node/flow.py
valid_flow_engine/engine/node/func.py
valid_flow_engine/engine/node/input.py
valid_flow_engine/engine/node/link.py
valid_flow_engine/engine/node/output.py
valid_flow_engine/engine/node/utils.py
valid_flow_engine/op_set_registry/__init__.py
valid_flow_engine/op_set_registry/processor.py
valid_flow_engine/op_sets/__init__.py
valid_flow_engine/op_sets/datetime.py
valid_flow_engine/op_sets/number.py
valid_flow_engine/op_sets/string.py
valid_flow_engine/types_registry/__init__.py
valid_flow_engine-0.1.25.dist-info/LICENSE
valid_flow_engine-0.1.25.dist-info/METADATA
valid_flow_engine-0.1.25.dist-info/WHEEL
valid_flow_engine-0.1.25.dist-info/top_level.txt
valid_flow_engine-0.1.25.dist-info/RECORD
