Metadata-Version: 2.1
Name: valid-flow-engine
Version: 0.1.25
Summary: Python Implementation of Valid Flow Engine
Home-page: https://github.com/jwaltgrant/py_valid_flow_engine
Author: Josh Grant
Author-email: jwaltgrant@gmail.com
License: GNU GPLv3
Platform: UNKNOWN
Classifier: License :: OSI Approved :: GNU General Public License v3 (GPLv3)
Classifier: Programming Language :: Python :: 3
Classifier: Programming Language :: Python :: 3.7
Requires-Dist: python-dateutil
